birdset/__init__.py
birdset/callbacks/__init__.py
birdset/callbacks/metric_collector.py
birdset/callbacks/timetracker.py
birdset/datamodule/__init__.py
birdset/datamodule/base_datamodule.py
birdset/datamodule/birdset_datamodule.py
birdset/datamodule/components/__init__.py
birdset/datamodule/components/augmentations.py
birdset/datamodule/components/bird_premapping.py
birdset/datamodule/components/calculate_normalization_parameters.py
birdset/datamodule/components/event_decoding.py
birdset/datamodule/components/event_mapping.py
birdset/datamodule/components/feature_extraction.py
birdset/datamodule/components/resize.py
birdset/datamodule/components/tests/test_augmentations.py
birdset/datamodule/components/transforms.py
birdset/datamodule/esc50_datamodule.py
birdset/datamodule/pretrain_datamodule.py
birdset/datamodule/subset_datamodules.py
"birdset/modules/__init__,py"
birdset/modules/__init__.py
birdset/modules/base_module.py
birdset/modules/components/__init__.py
birdset/modules/losses/__init__.py
birdset/modules/losses/asymmetric_loss.py
birdset/modules/losses/focal_loss.py
birdset/modules/losses/loader.py
birdset/modules/metrics/__init__.py
birdset/modules/metrics/loader.py
birdset/modules/metrics/multiclass.py
birdset/modules/metrics/multilabel.py
birdset/modules/models/__init__.py
birdset/modules/models/ast.py
birdset/modules/models/benchmark_models.py
birdset/modules/models/convnext.py
birdset/modules/models/eat_soundnet.py
birdset/modules/models/efficientnet.py
birdset/modules/models/hubert.py
birdset/modules/models/mobilenet.py
birdset/modules/models/perch.py
birdset/modules/models/resnet.py
birdset/modules/models/wav2vec2.py
birdset/modules/multilabel_module.py
birdset/train.py
birdset/utils/__init__.py
birdset/utils/extras.py
birdset/utils/instantiate.py
birdset/utils/label_utils.py
birdset/utils/pylogger.py
birdset/utils/rich_utils.py
birdset/utils/saving_utils.py
birdset/utils/utils.py
birdset-0.1.1.dist-info/METADATA
birdset-0.1.1.dist-info/WHEEL
birdset-0.1.1.dist-info/RECORD
