Metadata-Version: 2.1
Name: birdset
Version: 0.1.1
Summary: BirdSet: A multi-task benchmark and data pipeline for deep learning based avian bioacoustics
Author: Lukas Rauch
Author-email: lukas.rauch@uni-kassel.de
Requires-Python: >=3.10,<3.13
Classifier: Programming Language :: Python :: 3
Classifier: Programming Language :: Python :: 3.10
Classifier: Programming Language :: Python :: 3.11
Classifier: Programming Language :: Python :: 3.12
Requires-Dist: audiomentations (>=0.33.0,<0.34.0)
Requires-Dist: datasets (>=2.14.6,<3.0.0)
Requires-Dist: ffprobe (>=0.5,<0.6)
Requires-Dist: hydra-colorlog (>=1.2,<2.0)
Requires-Dist: hydra-core (>=1.3,<2.0)
Requires-Dist: hydra-optuna-sweeper (>=1.2,<2.0)
Requires-Dist: ipywidgets (>=8.1.1,<9.0.0)
Requires-Dist: jupyter (>=1.0.0,<2.0.0)
Requires-Dist: lightning (>=2.0,<3.0)
Requires-Dist: matplotlib (>=3.8.0,<4.0.0)
Requires-Dist: mlflow (>=2.11.0,<3.0.0)
Requires-Dist: pre-commit (>=3.5.0,<4.0.0)
Requires-Dist: pydub (>=0.25.1,<0.26.0)
Requires-Dist: pyrootutils (>=1.0.4,<2.0.0)
Requires-Dist: pytest (>=7.4.2,<8.0.0)
Requires-Dist: rich (>=13.6.0,<14.0.0)
Requires-Dist: rootutils (>=1.0.7,<2.0.0)
Requires-Dist: scipy (>=1.11.3,<2.0.0)
Requires-Dist: seaborn (>=0.13.0,<0.14.0)
Requires-Dist: sh (>=2.0.6,<3.0.0)
Requires-Dist: tensorboard (>=2.14.1,<3.0.0)
Requires-Dist: torch (>=2.1,<3.0)
Requires-Dist: torch-audiomentations (>=0.11.0,<0.12.0)
Requires-Dist: torchmetrics (>=0.11,<0.12)
Requires-Dist: torchvision (>=0.17,<0.18)
Requires-Dist: transformers (>=4.38.0,<5.0.0)
Requires-Dist: wandb (>=0.16.0,<0.17.0)
